minicloudstack/__init__.py
minicloudstack/addhost.py
minicloudstack/baremetal.py
minicloudstack/createzone.py
minicloudstack/deletezone.py
minicloudstack/mcs.py
minicloudstack/networkoffering.py
minicloudstack/registertemplate.py
minicloudstack/requester.py
minicloudstack/volume.py
minicloudstack-1.0.9.dist-info/DESCRIPTION.rst
minicloudstack-1.0.9.dist-info/entry_points.txt
minicloudstack-1.0.9.dist-info/METADATA
minicloudstack-1.0.9.dist-info/metadata.json
minicloudstack-1.0.9.dist-info/RECORD
minicloudstack-1.0.9.dist-info/top_level.txt
minicloudstack-1.0.9.dist-info/WHEEL
