Metadata-Version: 2.0
Name: minicloudstack
Version: 1.0.9
Summary: Minimal CloudStack Access Library and Utilities
Home-page: https://github.com/greenqloud/minicloudstack
Author: Greenqloud
Author-email: UNKNOWN
License: Apache
Keywords: cloudstack
Platform: UNKNOWN
Classifier: Development Status :: 5 - Production/Stable
Classifier: License :: OSI Approved :: Apache Software License
Classifier: Intended Audience :: Developers
Classifier: Operating System :: OS Independent
Classifier: Programming Language :: Python
Classifier: Programming Language :: Python :: 2
Classifier: Programming Language :: Python :: 2.7
Classifier: Programming Language :: Python :: 3
Classifier: Programming Language :: Python :: 3.5
Classifier: Topic :: Software Development :: Libraries :: Python Modules
Requires-Dist: requests-toolbelt (>=0.7.0)
